p24/__init__.py
p24/p24.py
24p-0.2.0.dist-info/LICENSE
24p-0.2.0.dist-info/METADATA
24p-0.2.0.dist-info/WHEEL
24p-0.2.0.dist-info/entry_points.txt
24p-0.2.0.dist-info/top_level.txt
24p-0.2.0.dist-info/RECORD
