Metadata-Version: 2.1
Name: 24p
Version: 0.2.0
Summary: 24Point
Home-page: https://github.com/lingjf/24p
Author: lingjf
Author-email: lingjf@gmail.com
License: UNKNOWN
Platform: UNKNOWN
Classifier: Programming Language :: Python :: 3
Classifier: License :: OSI Approved :: MIT License
Classifier: Operating System :: OS Independent
